pxyTools/__init__.py
pxyTools/dataIO.py
pxyTools/dataIO2.py
pxyTools/http2sql.py
pxyTools/make_pdf.py
pxyTools/object_cache.py
pxyTools/php_cache.py
pxyTools/round_robin.py
pxyTools/scheduler.py
pxyTools-1.1.9.dist-info/METADATA
pxyTools-1.1.9.dist-info/WHEEL
pxyTools-1.1.9.dist-info/top_level.txt
pxyTools-1.1.9.dist-info/RECORD
