Metadata-Version: 2.1
Name: pxyTools
Version: 1.1.9
Summary: A collection of python tools to save time on my personal projects
Home-page: https://github.com/Proxymiity/pxyTools-python
Download-URL: https://github.com/Proxymiity/pxyTools-python/releases
Author: Proxymiity
Author-email: dev@ayaya.red
License: MIT
Classifier: License :: OSI Approved :: MIT License
Classifier: Operating System :: OS Independent
Classifier: Programming Language :: Python :: 3.6
Classifier: Programming Language :: Python :: 3.7
Classifier: Programming Language :: Python :: 3.8
Classifier: Programming Language :: Python :: 3.9
Classifier: Programming Language :: Python :: 3.10
Classifier: Topic :: Internet
Classifier: Topic :: Software Development :: Libraries
Classifier: Topic :: Software Development :: Libraries :: Python Modules
Classifier: Topic :: Utilities
Classifier: Intended Audience :: Developers
Requires-Python: >=3.7
Requires-Dist: requests >=2.25.0
Provides-Extra: all
Requires-Dist: img2pdf >=0.4.3 ; extra == 'all'
Requires-Dist: Pillow >=8.4.0 ; extra == 'all'
Provides-Extra: pdf
Requires-Dist: img2pdf >=0.4.3 ; extra == 'pdf'
Requires-Dist: Pillow >=8.4.0 ; extra == 'pdf'
